thymus/__init__.py
thymus/__main__.py
thymus/contexts/__init__.py
thymus/contexts/context.py
thymus/contexts/eos.py
thymus/contexts/ios.py
thymus/contexts/junos.py
thymus/contexts/nxos.py
thymus/contexts/xros.py
thymus/lexers/__init__.py
thymus/lexers/common/__init__.py
thymus/lexers/common/common.py
thymus/lexers/common/regexps.py
thymus/lexers/ios/__init__.py
thymus/lexers/ios/ios.py
thymus/lexers/junos/__init__.py
thymus/lexers/junos/junos.py
thymus/modals/__init__.py
thymus/modals/context_list.py
thymus/modals/error_screen.py
thymus/modals/open_screen.py
thymus/modals/quit_screen.py
thymus/modals/settings_screen.py
thymus/netloader/__init__.py
thymus/netloader/dispatcher.py
thymus/netloader/exceptions.py
thymus/netloader/platforms/__init__.py
thymus/netloader/platforms/arista_eos.py
thymus/netloader/platforms/base.py
thymus/netloader/platforms/cisco_ios.py
thymus/netloader/platforms/cisco_nxos.py
thymus/netloader/platforms/juniper_junos.py
thymus/responses/__init__.py
thymus/responses/response.py
thymus/settings/__init__.py
thymus/settings/app_settings.py
thymus/settings/platforms.py
thymus/settings/settings.py
thymus/styles/main.css
thymus/templates/context_help.json
thymus/utils/__init__.py
thymus/utils/utils.py
thymus/working_screen/__init__.py
thymus/working_screen/command_line.py
thymus/working_screen/editor.py
thymus/working_screen/editor_overlay.py
thymus/working_screen/help.py
thymus/working_screen/path_bar.py
thymus/working_screen/screen_footer.py
thymus/working_screen/sidebar.py
thymus/working_screen/viewer.py
thymus/working_screen/working_screen.py
thymus-0.1.8.1.dist-info/LICENSE
thymus-0.1.8.1.dist-info/METADATA
thymus-0.1.8.1.dist-info/WHEEL
thymus-0.1.8.1.dist-info/RECORD
