Metadata-Version: 2.1
Name: thymus
Version: 0.1.8.1
Summary: Editor & browser for network configuration files
Author: Igor Malyushkin
Author-email: gmalyushkin@gmail.com
Requires-Python: >=3.9,<4.0
Classifier: Programming Language :: Python :: 3
Classifier: Programming Language :: Python :: 3.9
Classifier: Programming Language :: Python :: 3.10
Classifier: Programming Language :: Python :: 3.11
Classifier: Programming Language :: Python :: 3.12
Requires-Dist: asyncssh (>=2.14.1,<3.0.0)
Requires-Dist: bcrypt (>=4.1.1,<5.0.0)
Requires-Dist: msgpack (>=1.0.8,<2.0.0)
Requires-Dist: telnetlib3 (>=2.0.4,<3.0.0)
Requires-Dist: textual (==0.64.0)
Requires-Dist: thymus-ast (>=0.1.8.2,<0.2.0.0)
